pynlai/__init__.py
pynlai/cli.py
pynlai/core.py
pynlai/interface.py
pynlai/views.py
pynlai-0.1.2.dist-info/DESCRIPTION.rst
pynlai-0.1.2.dist-info/METADATA
pynlai-0.1.2.dist-info/RECORD
pynlai-0.1.2.dist-info/WHEEL
pynlai-0.1.2.dist-info/entry_points.txt
pynlai-0.1.2.dist-info/metadata.json
pynlai-0.1.2.dist-info/top_level.txt
