Metadata-Version: 2.0
Name: pynlai
Version: 0.1.2
Summary: PYthon Natural Language Application Interface library.
Home-page: https://github.com/alvarezandmarsal/pynlai
Author: Chris Pappalardo
Author-email: cpappalardo@alvarezandmarsal.com
License: MIT license
Keywords: pynlai
Platform: UNKNOWN
Classifier: Development Status :: 2 - Pre-Alpha
Classifier: Intended Audience :: Developers
Classifier: License :: OSI Approved :: MIT License
Classifier: Natural Language :: English
Classifier: Programming Language :: Python :: 2
Classifier: Programming Language :: Python :: 2.7
Classifier: Programming Language :: Python :: 3
Classifier: Programming Language :: Python :: 3.5
Requires-Dist: click
Requires-Dist: six
Requires-Dist: spacy
